timeflux_audio/__init__.py
timeflux_audio/nodes/__init__.py
timeflux_audio/nodes/device.py
timeflux_audio/nodes/signal.py
timeflux_audio-0.2.1.dist-info/LICENSE
timeflux_audio-0.2.1.dist-info/METADATA
timeflux_audio-0.2.1.dist-info/WHEEL
timeflux_audio-0.2.1.dist-info/top_level.txt
timeflux_audio-0.2.1.dist-info/RECORD
